bnsl/__init__.py
bnsl/accessory.py
bnsl/evaluation.py
bnsl/score.py
bnsl/structure_learning.py
bnsl-0.1.59.dist-info/LICENSE
bnsl-0.1.59.dist-info/METADATA
bnsl-0.1.59.dist-info/WHEEL
bnsl-0.1.59.dist-info/entry_points.txt
bnsl-0.1.59.dist-info/top_level.txt
bnsl-0.1.59.dist-info/RECORD
